deftree/__init__.py
deftree-2.1.4.dist-info/METADATA
deftree-2.1.4.dist-info/RECORD
deftree-2.1.4.dist-info/WHEEL
deftree-2.1.4.dist-info/top_level.txt
