Metadata-Version: 2.1
Name: deftree
Version: 2.1.4
Summary: Python module to modify Defold files
Home-page: https://github.com/Jerakin/DefTree
Author: Mattias.Hedberg
Author-email: hedberg.a.mattias@gmail.com
License: UNKNOWN
Keywords: defold deftree development
Platform: UNKNOWN
Classifier: Development Status :: 4 - Beta
Classifier: Intended Audience :: Developers
Classifier: Topic :: Software Development :: Build Tools
Classifier: License :: OSI Approved :: MIT License
Classifier: Programming Language :: Python :: 3.3
Classifier: Programming Language :: Python :: 3.4
Classifier: Programming Language :: Python :: 3.5
Classifier: Programming Language :: Python :: 3.6
Requires-Python: >=3
